aws_cost_optimization_4/__init__.py
aws_cost_optimization_4/utils.py
aws_cost_optimization_4-0.1.7.dist-info/LICENCE
aws_cost_optimization_4-0.1.7.dist-info/METADATA
aws_cost_optimization_4-0.1.7.dist-info/WHEEL
aws_cost_optimization_4-0.1.7.dist-info/top_level.txt
aws_cost_optimization_4-0.1.7.dist-info/RECORD
